setup.py
aux/__init__.py
aux/backend.py
aux/result.py
aux/scriptengine.py
aux/util.py
aux.egg-info/PKG-INFO
aux.egg-info/SOURCES.txt
aux.egg-info/dependency_links.txt
aux.egg-info/entry_points.txt
aux.egg-info/not-zip-safe
aux.egg-info/requires.txt
aux.egg-info/top_level.txt
aux/api/__init__.py
aux/authentication/__init__.py
aux/engine/__init__.py
aux/engine/actor/__init__.py
aux/engine/actor/base.py
aux/engine/actor/coactor.py
aux/engine/actor/proactor.py
aux/engine/actor/promise.py
aux/engine/actor/reactor.py
aux/internals/__init__.py
aux/internals/actor.py
aux/internals/configuration.py
aux/internals/credentials.py
aux/internals/pluginhook.py
aux/logger/__init__.py
aux/protocol/__init__.py
aux/protocol/transport.py
aux/protocol/webservice.py
aux/protocol/ext/__init__.py
aux/protocol/http/__init__.py
aux/protocol/http/http.py
aux/protocol/http/mime.py
aux/protocol/http/transfer.py
aux/protocol/http/auth/__init__.py
aux/protocol/http/auth/basic.py
aux/protocol/soap/__init__.py
aux/protocol/soap/soap.py
aux/protocol/soap/webservice.py
aux/protocol/soap/wsdl.py
aux/protocol/ssh/__init__.py
aux/protocol/ssh/ssh.py
aux/service/__init__.py
aux/service/servicefactory.py
aux/system/__init__.py
aux/system/base.py
aux/system/device/__init__.py
aux/system/device/endpoint.py
aux/system/device/linux.py
aux/system/device/network.py
aux/system/device/ext/__init__.py
aux/system/service/__init__.py
aux/system/service/ext/__init__.py
test/__init__.py
test/data/__init__.py
test/data/wsdl_raw_chunked_response.py
test/integration/__init__.py
test/integration/test_connection.py
test/integration/test_engine.py
test/integration/test_http_api.py
test/integration/test_http_protocol.py
test/integration/test_https_connection.py
test/integration/test_logging.py
test/integration/test_service_factory.py
test/unit/__init__.py
test/unit/test_http.py
test/unit/test_http_receive.py
test/unit/test_http_receive_long_wsdl.py
test/unit/test_wsdl.py
test/unit/test_wsdl_jsondl.py
test/unit/wsdldatatmp.py
test/util/__init__.py
test/util/mockhttpserver.py
test/util/test_mockhttpserver.py