Metadata-Version: 1.0
Name: aux
Version: 0.0.1
Summary: Automation Framework
Home-page: UNKNOWN
Author: email@protojour.com
Author-email: UNKNOWN
License: UNKNOWN
Keywords: TestCase Automation Device Network Protocol
Platform: UNKNOWN
